multicall_zksync/__init__.py
multicall_zksync/call.py
multicall_zksync/constants.py
multicall_zksync/exceptions.py
multicall_zksync/loggers.py
multicall_zksync/multicall.py
multicall_zksync/signature.py
multicall_zksync/utils.py
multicall_zksync-0.1.2.dist-info/WHEEL
multicall_zksync-0.1.2.dist-info/METADATA
multicall_zksync-0.1.2.dist-info/RECORD
