Metadata-Version: 2.1
Name: multicall-zksync
Version: 0.1.2
Summary: 
Author: JIVIN0902
Author-email: jivinvaidya@gmail.com
Requires-Python: >=3.8,<3.11
Classifier: Programming Language :: Python :: 3
Classifier: Programming Language :: Python :: 3.10
Classifier: Programming Language :: Python :: 3.8
Classifier: Programming Language :: Python :: 3.9
Requires-Dist: eth_retry (>=0.1.8,<0.2.0)
Requires-Dist: web3 (>=5.27,<6.0)
